gradientchat/__init__.py
gradientchat-2024.1.6.2.dist-info/METADATA
gradientchat-2024.1.6.2.dist-info/WHEEL
gradientchat-2024.1.6.2.dist-info/top_level.txt
gradientchat-2024.1.6.2.dist-info/RECORD
