Metadata-Version: 2.1
Name: gradientchat
Version: 2024.1.6.2
Summary: Bot Client for GradientChat
Author: RixTheTyrunt
Requires-Python: >=3
Requires-Dist: python-socketio
